<annotation>
	<folder>MINGGU</folder>
	<filename>image_DEK_UL270.jpg</filename>
	<path>D:\2.KULIAH\7.GARAP SKRIPSI MEI 2022\6.Gesture Bahasa isyarat code\4.VIDEO TRAIN\DATASET BOJO\HASIL_RECORD_DEK_UL - PERHARI\MINGGU\image_DEK_UL270.jpg</path>
	<source>
		<database>Unknown</database>
	</source>
	<size>
		<width>608</width>
		<height>1080</height>
		<depth>3</depth>
	</size>
	<segmented>0</segmented>
	<object>
		<name>MINGGU</name>
		<pose>Unspecified</pose>
		<truncated>0</truncated>
		<difficult>0</difficult>
		<bndbox>
			<xmin>149</xmin>
			<ymin>688</ymin>
			<xmax>331</xmax>
			<ymax>888</ymax>
		</bndbox>
	</object>
</annotation>
